fulladder.v
module fulladder(sum,cout,x,y,cin);
    input x,y,cin;
    output sum,cout;
    wire w[3:0];

    /*assign {cout,sum}=x+y+cin;
    assign sum=x^y^cin;
    assign cout=(x&y)||(cin&(x|y));*/
    xor G1(w[0],x,y), G2(sum,w[0],cin);
    and G3(w[1],x,y), G4(w[2],w[0],cin);
    or G5(cout,w[2],w[1]);
endmodule

adder8bit.v
//Designing 8-bit ripple carry adder using generate command
`include "fulladder.v"
module adder8bit(a,b,cin,cout,out);         //ANSI-C style Port declaration

    parameter n=8;
    input [n-1:0] a,b;
    input cin;
    output [n-1:0] out;
    output cout;
    wire [n:0] carry;

    assign carry[0]=cin;                    //Assigning input carry 
    assign cout=carry[n];                   //Assigning output carry

    genvar i;                              //generate variable

    generate for(i=0; i<n; i=i+1)          //generate for loop to create 8 Full adders
        begin
            fulladder FA0 (out[i],carry[i+1],a[i],b[i],carry[i]);           //Instantiating Full Adder module
        end
    endgenerate
endmodule

adder8bit_tb.v
`include "adder8bit.v"
module adder8bit_tb;
    reg [7:0] a,b;
    reg cin;
    wire [7:0] out;
    wire cout;
    integer i;

    adder8bit DUT(.a(a), .b(b), .cin(cin), .cout(cout), .out(out));

    initial
        begin
            $dumpfile("adder8bit_generate.vcd");
            $dumpvars(0,adder8bit_tb);
            $monitor($time," A=%h | B=%h | Carry_in=%b | OUTPUT=%h | Carry_out=%b",a,b,cin,out,cout);
            a=8'h01; b=8'h01; cin=1'b0;
            for(i=0; i<87; i=i+1)
                begin
                    a=i; b=i+1; #1;
                end
            $finish;
            //$finish;
        end
endmodule

adder8bit_generate.vcd
$date
	Wed Sep 18 18:12:55 2024
$end
$version
	Icarus Verilog
$end
$timescale
	1s
$end
$scope module adder8bit_tb $end
$var wire 8 ! out [7:0] $end
$var wire 1 " cout $end
$var reg 8 # a [7:0] $end
$var reg 8 $ b [7:0] $end
$var reg 1 % cin $end
$var integer 32 & i [31:0] $end
$scope module DUT $end
$var wire 8 ' a [7:0] $end
$var wire 8 ( b [7:0] $end
$var wire 1 % cin $end
$var wire 8 ) out [7:0] $end
$var wire 1 " cout $end
$var wire 9 * carry [8:0] $end
$var parameter 32 + n $end
$scope begin genblk1[0] $end
$var parameter 2 , i $end
$scope module FA0 $end
$var wire 1 - cin $end
$var wire 1 . cout $end
$var wire 1 / sum $end
$var wire 1 0 x $end
$var wire 1 1 y $end
$upscope $end
$upscope $end
$scope begin genblk1[1] $end
$var parameter 2 2 i $end
$scope module FA0 $end
$var wire 1 3 cin $end
$var wire 1 4 cout $end
$var wire 1 5 sum $end
$var wire 1 6 x $end
$var wire 1 7 y $end
$upscope $end
$upscope $end
$scope begin genblk1[2] $end
$var parameter 3 8 i $end
$scope module FA0 $end
$var wire 1 9 cin $end
$var wire 1 : cout $end
$var wire 1 ; sum $end
$var wire 1 < x $end
$var wire 1 = y $end
$upscope $end
$upscope $end
$scope begin genblk1[3] $end
$var parameter 3 > i $end
$scope module FA0 $end
$var wire 1 ? cin $end
$var wire 1 @ cout $end
$var wire 1 A sum $end
$var wire 1 B x $end
$var wire 1 C y $end
$upscope $end
$upscope $end
$scope begin genblk1[4] $end
$var parameter 4 D i $end
$scope module FA0 $end
$var wire 1 E cin $end
$var wire 1 F cout $end
$var wire 1 G sum $end
$var wire 1 H x $end
$var wire 1 I y $end
$upscope $end
$upscope $end
$scope begin genblk1[5] $end
$var parameter 4 J i $end
$scope module FA0 $end
$var wire 1 K cin $end
$var wire 1 L cout $end
$var wire 1 M sum $end
$var wire 1 N x $end
$var wire 1 O y $end
$upscope $end
$upscope $end
$scope begin genblk1[6] $end
$var parameter 4 P i $end
$scope module FA0 $end
$var wire 1 Q cin $end
$var wire 1 R cout $end
$var wire 1 S sum $end
$var wire 1 T x $end
$var wire 1 U y $end
$upscope $end
$upscope $end
$scope begin genblk1[7] $end
$var parameter 4 V i $end
$scope module FA0 $end
$var wire 1 W cin $end
$var wire 1 X cout $end
$var wire 1 Y sum $end
$var wire 1 Z x $end
$var wire 1 [ y $end
$upscope $end
$upscope $end
$upscope $end
$upscope $end
$enddefinitions $end
$comment Show the parameter values. $end
$dumpall
b111 V
b110 P
b101 J
b100 D
b11 >
b10 8
b1 2
b0 ,
b1000 +
$end
#0
$dumpvars
0[
0Z
0Y
0X
0W
0U
0T
0S
0R
0Q
0O
0N
0M
0L
0K
0I
0H
0G
0F
0E
0C
0B
0A
0@
0?
0=
0<
0;
0:
09
07
06
05
04
03
11
00
1/
0.
0-
b0 *
b1 )
b1 (
b0 '
b0 &
0%
b1 $
b0 #
0"
b1 !
$end
#1
b11 !
b11 )
15
01
17
10
b10 $
b10 (
b1 #
b1 '
b1 &
#2
1;
19
b101 !
b101 )
05
b100 *
14
11
00
16
b11 $
b11 (
b10 #
b10 '
b10 &
#3
0A
0?
09
0:
15
b0 *
04
b111 !
b111 )
1;
01
07
1=
10
b100 $
b100 (
b11 #
b11 '
b11 &
#4
1A
1?
05
b1001 !
b1001 )
0;
b1000 *
1:
11
00
06
1<
b101 $
b101 (
b100 #
b100 '
b100 &
#5
b1011 !
b1011 )
15
01
17
10
b110 $
b110 (
b101 #
b101 '
b101 &
#6
1;
19
b1101 !
b1101 )
05
b1100 *
14
11
00
16
b111 $
b111 (
b110 #
b110 '
b110 &
#7
0G
0E
09
0?
0@
15
04
1;
b0 *
0:
b1111 !
b1111 )
1A
01
07
0=
1C
10
b1000 $
b1000 (
b111 #
b111 '
b111 &
#8
1G
1E
05
0;
b10001 !
b10001 )
0A
b10000 *
1@
11
00
06
0<
1B
b1001 $
b1001 (
b1000 #
b1000 '
b1000 &
#9
b10011 !
b10011 )
15
01
17
10
b1010 $
b1010 (
b1001 #
b1001 '
b1001 &
#10
1;
19
b10101 !
b10101 )
05
b10100 *
14
11
00
16
b1011 $
b1011 (
b1010 #
b1010 '
b1010 &
#11
0A
0?
09
0:
15
b10000 *
04
b10111 !
b10111 )
1;
01
07
1=
10
b1100 $
b1100 (
b1011 #
b1011 '
b1011 &
#12
1A
1?
05
b11001 !
b11001 )
0;
b11000 *
1:
11
00
06
1<
b1101 $
b1101 (
b1100 #
b1100 '
b1100 &
#13
b11011 !
b11011 )
15
01
17
10
b1110 $
b1110 (
b1101 #
b1101 '
b1101 &
#14
1;
19
b11101 !
b11101 )
05
b11100 *
14
11
00
16
b1111 $
b1111 (
b1110 #
b1110 '
b1110 &
#15
0M
0K
09
0?
0E
0F
15
04
1;
0:
1A
b0 *
0@
b11111 !
b11111 )
1G
01
07
0=
0C
1I
10
b10000 $
b10000 (
b1111 #
b1111 '
b1111 &
#16
1M
1K
05
0;
0A
b100001 !
b100001 )
0G
b100000 *
1F
11
00
06
0<
0B
1H
b10001 $
b10001 (
b10000 #
b10000 '
b10000 &
#17
b100011 !
b100011 )
15
01
17
10
b10010 $
b10010 (
b10001 #
b10001 '
b10001 &
#18
1;
19
b100101 !
b100101 )
05
b100100 *
14
11
00
16
b10011 $
b10011 (
b10010 #
b10010 '
b10010 &
#19
0A
0?
09
0:
15
b100000 *
04
b100111 !
b100111 )
1;
01
07
1=
10
b10100 $
b10100 (
b10011 #
b10011 '
b10011 &
#20
1A
1?
05
b101001 !
b101001 )
0;
b101000 *
1:
11
00
06
1<
b10101 $
b10101 (
b10100 #
b10100 '
b10100 &
#21
b101011 !
b101011 )
15
01
17
10
b10110 $
b10110 (
b10101 #
b10101 '
b10101 &
#22
1;
19
b101101 !
b101101 )
05
b101100 *
14
11
00
16
b10111 $
b10111 (
b10110 #
b10110 '
b10110 &
#23
0G
0E
09
0?
0@
15
04
1;
b100000 *
0:
b101111 !
b101111 )
1A
01
07
0=
1C
10
b11000 $
b11000 (
b10111 #
b10111 '
b10111 &
#24
1G
1E
05
0;
b110001 !
b110001 )
0A
b110000 *
1@
11
00
06
0<
1B
b11001 $
b11001 (
b11000 #
b11000 '
b11000 &
#25
b110011 !
b110011 )
15
01
17
10
b11010 $
b11010 (
b11001 #
b11001 '
b11001 &
#26
1;
19
b110101 !
b110101 )
05
b110100 *
14
11
00
16
b11011 $
b11011 (
b11010 #
b11010 '
b11010 &
#27
0A
0?
09
0:
15
b110000 *
04
b110111 !
b110111 )
1;
01
07
1=
10
b11100 $
b11100 (
b11011 #
b11011 '
b11011 &
#28
1A
1?
05
b111001 !
b111001 )
0;
b111000 *
1:
11
00
06
1<
b11101 $
b11101 (
b11100 #
b11100 '
b11100 &
#29
b111011 !
b111011 )
15
01
17
10
b11110 $
b11110 (
b11101 #
b11101 '
b11101 &
#30
1;
19
b111101 !
b111101 )
05
b111100 *
14
11
00
16
b11111 $
b11111 (
b11110 #
b11110 '
b11110 &
#31
0S
0Q
09
0?
0E
0K
0L
15
04
1;
0:
1A
0@
1G
b0 *
0F
b111111 !
b111111 )
1M
01
07
0=
0C
0I
1O
10
b100000 $
b100000 (
b11111 #
b11111 '
b11111 &
#32
1S
1Q
05
0;
0A
0G
b1000001 !
b1000001 )
0M
b1000000 *
1L
11
00
06
0<
0B
0H
1N
b100001 $
b100001 (
b100000 #
b100000 '
b100000 &
#33
b1000011 !
b1000011 )
15
01
17
10
b100010 $
b100010 (
b100001 #
b100001 '
b100001 &
#34
1;
19
b1000101 !
b1000101 )
05
b1000100 *
14
11
00
16
b100011 $
b100011 (
b100010 #
b100010 '
b100010 &
#35
0A
0?
09
0:
15
b1000000 *
04
b1000111 !
b1000111 )
1;
01
07
1=
10
b100100 $
b100100 (
b100011 #
b100011 '
b100011 &
#36
1A
1?
05
b1001001 !
b1001001 )
0;
b1001000 *
1:
11
00
06
1<
b100101 $
b100101 (
b100100 #
b100100 '
b100100 &
#37
b1001011 !
b1001011 )
15
01
17
10
b100110 $
b100110 (
b100101 #
b100101 '
b100101 &
#38
1;
19
b1001101 !
b1001101 )
05
b1001100 *
14
11
00
16
b100111 $
b100111 (
b100110 #
b100110 '
b100110 &
#39
0G
0E
09
0?
0@
15
04
1;
b1000000 *
0:
b1001111 !
b1001111 )
1A
01
07
0=
1C
10
b101000 $
b101000 (
b100111 #
b100111 '
b100111 &
#40
1G
1E
05
0;
b1010001 !
b1010001 )
0A
b1010000 *
1@
11
00
06
0<
1B
b101001 $
b101001 (
b101000 #
b101000 '
b101000 &
#41
b1010011 !
b1010011 )
15
01
17
10
b101010 $
b101010 (
b101001 #
b101001 '
b101001 &
#42
1;
19
b1010101 !
b1010101 )
05
b1010100 *
14
11
00
16
b101011 $
b101011 (
b101010 #
b101010 '
b101010 &
#43
0A
0?
09
0:
15
b1010000 *
04
b1010111 !
b1010111 )
1;
01
07
1=
10
b101100 $
b101100 (
b101011 #
b101011 '
b101011 &
#44
1A
1?
05
b1011001 !
b1011001 )
0;
b1011000 *
1:
11
00
06
1<
b101101 $
b101101 (
b101100 #
b101100 '
b101100 &
#45
b1011011 !
b1011011 )
15
01
17
10
b101110 $
b101110 (
b101101 #
b101101 '
b101101 &
#46
1;
19
b1011101 !
b1011101 )
05
b1011100 *
14
11
00
16
b101111 $
b101111 (
b101110 #
b101110 '
b101110 &
#47
0M
0K
09
0?
0E
0F
15
04
1;
0:
1A
b1000000 *
0@
b1011111 !
b1011111 )
1G
01
07
0=
0C
1I
10
b110000 $
b110000 (
b101111 #
b101111 '
b101111 &
#48
1M
1K
05
0;
0A
b1100001 !
b1100001 )
0G
b1100000 *
1F
11
00
06
0<
0B
1H
b110001 $
b110001 (
b110000 #
b110000 '
b110000 &
#49
b1100011 !
b1100011 )
15
01
17
10
b110010 $
b110010 (
b110001 #
b110001 '
b110001 &
#50
1;
19
b1100101 !
b1100101 )
05
b1100100 *
14
11
00
16
b110011 $
b110011 (
b110010 #
b110010 '
b110010 &
#51
0A
0?
09
0:
15
b1100000 *
04
b1100111 !
b1100111 )
1;
01
07
1=
10
b110100 $
b110100 (
b110011 #
b110011 '
b110011 &
#52
1A
1?
05
b1101001 !
b1101001 )
0;
b1101000 *
1:
11
00
06
1<
b110101 $
b110101 (
b110100 #
b110100 '
b110100 &
#53
b1101011 !
b1101011 )
15
01
17
10
b110110 $
b110110 (
b110101 #
b110101 '
b110101 &
#54
1;
19
b1101101 !
b1101101 )
05
b1101100 *
14
11
00
16
b110111 $
b110111 (
b110110 #
b110110 '
b110110 &
#55
0G
0E
09
0?
0@
15
04
1;
b1100000 *
0:
b1101111 !
b1101111 )
1A
01
07
0=
1C
10
b111000 $
b111000 (
b110111 #
b110111 '
b110111 &
#56
1G
1E
05
0;
b1110001 !
b1110001 )
0A
b1110000 *
1@
11
00
06
0<
1B
b111001 $
b111001 (
b111000 #
b111000 '
b111000 &
#57
b1110011 !
b1110011 )
15
01
17
10
b111010 $
b111010 (
b111001 #
b111001 '
b111001 &
#58
1;
19
b1110101 !
b1110101 )
05
b1110100 *
14
11
00
16
b111011 $
b111011 (
b111010 #
b111010 '
b111010 &
#59
0A
0?
09
0:
15
b1110000 *
04
b1110111 !
b1110111 )
1;
01
07
1=
10
b111100 $
b111100 (
b111011 #
b111011 '
b111011 &
#60
1A
1?
05
b1111001 !
b1111001 )
0;
b1111000 *
1:
11
00
06
1<
b111101 $
b111101 (
b111100 #
b111100 '
b111100 &
#61
b1111011 !
b1111011 )
15
01
17
10
b111110 $
b111110 (
b111101 #
b111101 '
b111101 &
#62
1;
19
b1111101 !
b1111101 )
05
b1111100 *
14
11
00
16
b111111 $
b111111 (
b111110 #
b111110 '
b111110 &
#63
0Y
0W
09
0?
0E
0K
0Q
0R
15
04
1;
0:
1A
0@
1G
0F
1M
b0 *
0L
b1111111 !
b1111111 )
1S
01
07
0=
0C
0I
0O
1U
10
b1000000 $
b1000000 (
b111111 #
b111111 '
b111111 &
#64
1Y
1W
05
0;
0A
0G
0M
b10000001 !
b10000001 )
0S
b10000000 *
1R
11
00
06
0<
0B
0H
0N
1T
b1000001 $
b1000001 (
b1000000 #
b1000000 '
b1000000 &
#65
b10000011 !
b10000011 )
15
01
17
10
b1000010 $
b1000010 (
b1000001 #
b1000001 '
b1000001 &
#66
1;
19
b10000101 !
b10000101 )
05
b10000100 *
14
11
00
16
b1000011 $
b1000011 (
b1000010 #
b1000010 '
b1000010 &
#67
0A
0?
09
0:
15
b10000000 *
04
b10000111 !
b10000111 )
1;
01
07
1=
10
b1000100 $
b1000100 (
b1000011 #
b1000011 '
b1000011 &
#68
1A
1?
05
b10001001 !
b10001001 )
0;
b10001000 *
1:
11
00
06
1<
b1000101 $
b1000101 (
b1000100 #
b1000100 '
b1000100 &
#69
b10001011 !
b10001011 )
15
01
17
10
b1000110 $
b1000110 (
b1000101 #
b1000101 '
b1000101 &
#70
1;
19
b10001101 !
b10001101 )
05
b10001100 *
14
11
00
16
b1000111 $
b1000111 (
b1000110 #
b1000110 '
b1000110 &
#71
0G
0E
09
0?
0@
15
04
1;
b10000000 *
0:
b10001111 !
b10001111 )
1A
01
07
0=
1C
10
b1001000 $
b1001000 (
b1000111 #
b1000111 '
b1000111 &
#72
1G
1E
05
0;
b10010001 !
b10010001 )
0A
b10010000 *
1@
11
00
06
0<
1B
b1001001 $
b1001001 (
b1001000 #
b1001000 '
b1001000 &
#73
b10010011 !
b10010011 )
15
01
17
10
b1001010 $
b1001010 (
b1001001 #
b1001001 '
b1001001 &
#74
1;
19
b10010101 !
b10010101 )
05
b10010100 *
14
11
00
16
b1001011 $
b1001011 (
b1001010 #
b1001010 '
b1001010 &
#75
0A
0?
09
0:
15
b10010000 *
04
b10010111 !
b10010111 )
1;
01
07
1=
10
b1001100 $
b1001100 (
b1001011 #
b1001011 '
b1001011 &
#76
1A
1?
05
b10011001 !
b10011001 )
0;
b10011000 *
1:
11
00
06
1<
b1001101 $
b1001101 (
b1001100 #
b1001100 '
b1001100 &
#77
b10011011 !
b10011011 )
15
01
17
10
b1001110 $
b1001110 (
b1001101 #
b1001101 '
b1001101 &
#78
1;
19
b10011101 !
b10011101 )
05
b10011100 *
14
11
00
16
b1001111 $
b1001111 (
b1001110 #
b1001110 '
b1001110 &
#79
0M
0K
09
0?
0E
0F
15
04
1;
0:
1A
b10000000 *
0@
b10011111 !
b10011111 )
1G
01
07
0=
0C
1I
10
b1010000 $
b1010000 (
b1001111 #
b1001111 '
b1001111 &
#80
1M
1K
05
0;
0A
b10100001 !
b10100001 )
0G
b10100000 *
1F
11
00
06
0<
0B
1H
b1010001 $
b1010001 (
b1010000 #
b1010000 '
b1010000 &
#81
b10100011 !
b10100011 )
15
01
17
10
b1010010 $
b1010010 (
b1010001 #
b1010001 '
b1010001 &
#82
1;
19
b10100101 !
b10100101 )
05
b10100100 *
14
11
00
16
b1010011 $
b1010011 (
b1010010 #
b1010010 '
b1010010 &
#83
0A
0?
09
0:
15
b10100000 *
04
b10100111 !
b10100111 )
1;
01
07
1=
10
b1010100 $
b1010100 (
b1010011 #
b1010011 '
b1010011 &
#84
1A
1?
05
b10101001 !
b10101001 )
0;
b10101000 *
1:
11
00
06
1<
b1010101 $
b1010101 (
b1010100 #
b1010100 '
b1010100 &
#85
b10101011 !
b10101011 )
15
01
17
10
b1010110 $
b1010110 (
b1010101 #
b1010101 '
b1010101 &
#86
1;
19
b10101101 !
b10101101 )
05
b10101100 *
14
11
00
16
b1010111 $
b1010111 (
b1010110 #
b1010110 '
b1010110 &
#87
b1010111 &
