fulladder.v
module fulladder(sum,cout,x,y,cin);
    input x,y,cin;
    output sum,cout;
    wire w[3:0];

    /*assign {cout,sum}=x+y+cin;
    assign sum=x^y^cin;
    assign cout=(x&y)||(cin&(x|y));*/
    xor G1(w[0],x,y), G2(sum,w[0],cin);
    and G3(w[1],x,y), G4(w[2],w[0],cin);
    or G5(cout,w[2],w[1]);
endmodule

fulladder_tb.v
`include "fulladder.v"
module fulladder_tb;
    reg x,y,cin;
    wire sum,cout;

    fulladder DUT(sum,cout,x,y,cin);

    initial
        begin
            $dumpfile("fulladder.vcd");
            $dumpvars(0,fulladder_tb);
            $monitor($time," Sum=%b, Cout=%b, X=%b, Y=%b, Cin=%b",sum,cout,x,y,cin);
            #5 x=1'b0; y=1'b0; cin=1'b0;
            #10 x=1'b0; y=1'b0; cin=1'b1;
            #15 x=1'b0; y=1'b1; cin=1'b0;
            #20 x=1'b0; y=1'b1; cin=1'b1;
            #25 x=1'b1; y=1'b0; cin=1'b0;
            #30 x=1'b1; y=1'b0; cin=1'b1;
            #35 x=1'b1; y=1'b1; cin=1'b0;
            #40 x=1'b1; y=1'b1; cin=1'b1;
            #45 $finish;
        end
endmodule

fulladder.vcd
$date
	Sat Jun 15 17:48:41 2024
$end
$version
	Icarus Verilog
$end
$timescale
	1s
$end
$scope module fulladder_tb $end
$var wire 1 ! sum $end
$var wire 1 " cout $end
$var reg 1 # cin $end
$var reg 1 $ x $end
$var reg 1 % y $end
$scope module DUT $end
$var wire 1 # cin $end
$var wire 1 " cout $end
$var wire 1 ! sum $end
$var wire 1 $ x $end
$var wire 1 % y $end
$upscope $end
$upscope $end
$enddefinitions $end
$comment Show the parameter values. $end
$dumpall
$end
#0
$dumpvars
x%
x$
x#
x"
x!
$end
#5
0"
0!
0#
0%
0$
#15
1!
1#
#30
0#
1%
#50
1"
0!
1#
#75
0"
1!
0#
0%
1$
#105
1"
0!
1#
#140
0#
1%
#180
1!
1#
