jk_ff.v
//JK-FF with Active Low Asynchronous Preset and Clear
module jk_ff(clk,j,k,preset,clear,q);
    input clk,j,k,preset,clear;
    output reg q;

    always @(negedge clk , preset, clear)
        begin
            if(!preset)         //Active Low Asynchronous Preset
                begin
                    q<=1;
                    //qbar<=0;
                end
            else if(!clear)     //Active Low Asynchronous Clear
                begin
                    q<=0;
                    //qbar<=1;
                end
            else 
                begin
                    case({j,k})
                        2'b00: q<=q;    //No Change
                        2'b01: q<=0;    //Reset
                        2'b10: q<=1;    //Set
                        2'b11: q<=~q;   //Toggle Case
                    endcase
                    //qbar<=~q;
                end
            //qbar<=~q;
        end
        
endmodule

jkff_tb.v
`include "jk_ff.v"
module jkff_tb;
    reg clk,j,k,preset,clear;
    wire q;

    jk_ff DUT(clk,j,k,preset,clear,q);

    always #5 clk=~clk;

    initial
        begin 
            $dumpfile("jk_ff.vcd");
            $dumpvars(0,jkff_tb);
            $monitor($time," CLOCK=%b ,J=%b, F=%b, PRESET=%b, CLEAR=%b, Q=%b",clk,j,k,preset,clear,q);
            clk=1; j=0; k=0; preset=1; clear=0;
            #8 preset=1; clear=1; j=1; k=1;
            /*#10 preset=1; clear=1; j=1; k=1;
            #15 preset=1; clear=1; j=1; k=1;
            #20 preset=1; clear=1; j=1; k=1;
            #30 preset=1; clear=1; j=1; k=1;
            #35 preset=1; clear=1; j=1; k=1;
            #40 preset=1; clear=1; j=1; k=1;
            #45 preset=1; clear=1; j=1; k=1;*/
        end
    initial 
        #100 $finish;
endmodule

jk_ff.vcd
$date
	Thu Sep 12 18:37:03 2024
$end
$version
	Icarus Verilog
$end
$timescale
	1s
$end
$scope module jkff_tb $end
$var wire 1 ! q $end
$var reg 1 " clear $end
$var reg 1 # clk $end
$var reg 1 $ j $end
$var reg 1 % k $end
$var reg 1 & preset $end
$scope module DUT $end
$var wire 1 " clear $end
$var wire 1 # clk $end
$var wire 1 $ j $end
$var wire 1 % k $end
$var wire 1 & preset $end
$var reg 1 ! q $end
$upscope $end
$upscope $end
$enddefinitions $end
$comment Show the parameter values. $end
$dumpall
$end
#0
$dumpvars
1&
0%
0$
1#
0"
0!
$end
#5
0#
#8
1!
1%
1$
1"
#10
1#
#15
0!
0#
#20
1#
#25
1!
0#
#30
1#
#35
0!
0#
#40
1#
#45
1!
0#
#50
1#
#55
0!
0#
#60
1#
#65
1!
0#
#70
1#
#75
0!
0#
#80
1#
#85
1!
0#
#90
1#
#95
0!
0#
